{
  "kind": "singleType",
  "collectionName": "terms_pages",
  "info": {
    "singularName": "terms-page",
    "pluralName": "terms-pages",
    "displayName": "Terms page",
    "description": ""
  },
  "options": {
    "draftAndPublish": false
  },
  "pluginOptions": {
    "i18n": {
      "localized": true
    }
  },
  "attributes": {
    "content": {
      "type": "blocks",
      "required": true,
      "pluginOptions": {
        "i18n": {
          "localized": true
        }
      }
    }
  }
}
